{
    "extension": "linecounter",
    "version": "0.2.7",
    "workspace": "c:\\Users\\Peter\\Documents\\ReactProjects\\retrospective.react",
    "linecount": [
        {
            "version": "0.2.7",
            "counttime": "2023-05-21 22:03:30",
            "filesum": 54,
            "codesum": 17655,
            "commentsum": 26,
            "blanksum": 100,
            "statistics": {
                ".json": {
                    "code": 17140,
                    "comment": 0,
                    "blank": 7
                },
                ".md": {
                    "code": 26,
                    "comment": 6,
                    "blank": 20
                },
                "": {
                    "code": 18,
                    "comment": 1,
                    "blank": 5
                },
                ".tsx": {
                    "code": 279,
                    "comment": 0,
                    "blank": 47
                },
                ".css": {
                    "code": 104,
                    "comment": 0,
                    "blank": 14
                },
                ".ts": {
                    "code": 63,
                    "comment": 5,
                    "blank": 7
                },
                ".txt": {
                    "code": 3,
                    "comment": 1,
                    "blank": 0
                },
                ".html": {
                    "code": 22,
                    "comment": 13,
                    "blank": 0
                }
            },
            "filelist": [
                {
                    "blank": 5,
                    "code": 18,
                    "comment": 1,
                    "filename": ".gitignore"
                },
                {
                    "blank": 2,
                    "code": 17067,
                    "comment": 0,
                    "filename": "package-lock.json"
                },
                {
                    "blank": 3,
                    "code": 40,
                    "comment": 0,
                    "filename": "package.json"
                },
                {
                    "blank": 0,
                    "code": 22,
                    "comment": 13,
                    "filename": "public\\index.html"
                },
                {
                    "blank": 0,
                    "code": 9,
                    "comment": 0,
                    "filename": "public\\manifest.json"
                },
                {
                    "blank": 0,
                    "code": 3,
                    "comment": 1,
                    "filename": "public\\robots.txt"
                },
                {
                    "blank": 20,
                    "code": 26,
                    "comment": 6,
                    "filename": "README.md"
                },
                {
                    "blank": 0,
                    "code": 2,
                    "comment": 0,
                    "filename": "src\\App.css"
                },
                {
                    "blank": 2,
                    "code": 9,
                    "comment": 0,
                    "filename": "src\\App.tsx"
                },
                {
                    "blank": 0,
                    "code": 4,
                    "comment": 0,
                    "filename": "src\\components\\card\\Card.module.css"
                },
                {
                    "blank": 2,
                    "code": 10,
                    "comment": 0,
                    "filename": "src\\components\\card\\Card.tsx"
                },
                {
                    "blank": 1,
                    "code": 5,
                    "comment": 0,
                    "filename": "src\\components\\card\\ICardProps.ts"
                },
                {
                    "blank": 0,
                    "code": 4,
                    "comment": 0,
                    "filename": "src\\components\\input\\IInputProps.ts"
                },
                {
                    "blank": 2,
                    "code": 14,
                    "comment": 0,
                    "filename": "src\\components\\input\\Input.tsx"
                },
                {
                    "blank": 2,
                    "code": 11,
                    "comment": 0,
                    "filename": "src\\features\\board\\Board.module.css"
                },
                {
                    "blank": 3,
                    "code": 28,
                    "comment": 0,
                    "filename": "src\\features\\board\\Board.tsx"
                },
                {
                    "blank": 0,
                    "code": 4,
                    "comment": 0,
                    "filename": "src\\features\\boardSection\\BoardSection.module.css"
                },
                {
                    "blank": 2,
                    "code": 11,
                    "comment": 0,
                    "filename": "src\\features\\boardSection\\BoardSection.tsx"
                },
                {
                    "blank": 0,
                    "code": 5,
                    "comment": 0,
                    "filename": "src\\features\\boardSection\\IBoardSectionProps.ts"
                },
                {
                    "blank": 2,
                    "code": 15,
                    "comment": 0,
                    "filename": "src\\features\\BoardTitle\\BoardTitle.module.css"
                },
                {
                    "blank": 5,
                    "code": 32,
                    "comment": 0,
                    "filename": "src\\features\\BoardTitle\\BoardTitle.tsx"
                },
                {
                    "blank": 0,
                    "code": 3,
                    "comment": 0,
                    "filename": "src\\features\\BoardTitle\\IBoardTitleProps.ts"
                },
                {
                    "blank": 1,
                    "code": 8,
                    "comment": 0,
                    "filename": "src\\features\\comment\\Comment.module.css"
                },
                {
                    "blank": 2,
                    "code": 13,
                    "comment": 0,
                    "filename": "src\\features\\comment\\Comment.tsx"
                },
                {
                    "blank": 1,
                    "code": 5,
                    "comment": 0,
                    "filename": "src\\features\\comment\\ICommentProps.ts"
                },
                {
                    "blank": 3,
                    "code": 16,
                    "comment": 0,
                    "filename": "src\\features\\commentFooter\\CommentFooter.module.css"
                },
                {
                    "blank": 4,
                    "code": 25,
                    "comment": 0,
                    "filename": "src\\features\\commentFooter\\CommentFooter.tsx"
                },
                {
                    "blank": 1,
                    "code": 4,
                    "comment": 0,
                    "filename": "src\\features\\commentFooter\\ICommentFooterProps.ts"
                },
                {
                    "blank": 2,
                    "code": 10,
                    "comment": 0,
                    "filename": "src\\features\\commentInput\\CommentInput.module.css"
                },
                {
                    "blank": 6,
                    "code": 31,
                    "comment": 0,
                    "filename": "src\\features\\commentInput\\CommentInput.tsx"
                },
                {
                    "blank": 0,
                    "code": 4,
                    "comment": 0,
                    "filename": "src\\features\\commentInput\\ICommentInputProps.ts"
                },
                {
                    "blank": 2,
                    "code": 13,
                    "comment": 0,
                    "filename": "src\\features\\commentList\\CommentList.tsx"
                },
                {
                    "blank": 0,
                    "code": 5,
                    "comment": 0,
                    "filename": "src\\features\\commentList\\ICommentListProps.ts"
                },
                {
                    "blank": 4,
                    "code": 16,
                    "comment": 0,
                    "filename": "src\\features\\commentSection\\CommentSection.tsx"
                },
                {
                    "blank": 1,
                    "code": 5,
                    "comment": 0,
                    "filename": "src\\features\\commentSection\\ICommentSectionProps.ts"
                },
                {
                    "blank": 0,
                    "code": 3,
                    "comment": 0,
                    "filename": "src\\features\\voting\\votingButton\\agreeButton\\AgreeButton.module.css"
                },
                {
                    "blank": 2,
                    "code": 9,
                    "comment": 0,
                    "filename": "src\\features\\voting\\votingButton\\agreeButton\\AgreeButton.tsx"
                },
                {
                    "blank": 1,
                    "code": 2,
                    "comment": 0,
                    "filename": "src\\features\\voting\\votingButton\\agreeButton\\IAgreeButtonProps.ts"
                },
                {
                    "blank": 0,
                    "code": 5,
                    "comment": 0,
                    "filename": "src\\features\\voting\\votingButton\\components\\IBaseVotingButtonProps.ts"
                },
                {
                    "blank": 1,
                    "code": 5,
                    "comment": 0,
                    "filename": "src\\features\\voting\\votingButton\\components\\IVotingButtonProps.ts"
                },
                {
                    "blank": 3,
                    "code": 16,
                    "comment": 0,
                    "filename": "src\\features\\voting\\votingButton\\components\\VotingButton.module.css"
                },
                {
                    "blank": 2,
                    "code": 15,
                    "comment": 0,
                    "filename": "src\\features\\voting\\votingButton\\components\\VotingButton.tsx"
                },
                {
                    "blank": 0,
                    "code": 3,
                    "comment": 0,
                    "filename": "src\\features\\voting\\votingButton\\disagreeButton\\DisagreeButton.module.css"
                },
                {
                    "blank": 2,
                    "code": 13,
                    "comment": 0,
                    "filename": "src\\features\\voting\\votingButton\\disagreeButton\\DisagreeButton.tsx"
                },
                {
                    "blank": 1,
                    "code": 2,
                    "comment": 0,
                    "filename": "src\\features\\voting\\votingButton\\disagreeButton\\IDisagreeButtonProps.ts"
                },
                {
                    "blank": 0,
                    "code": 3,
                    "comment": 0,
                    "filename": "src\\features\\voting\\votingSection\\IVotingSectionProps.ts"
                },
                {
                    "blank": 4,
                    "code": 28,
                    "comment": 0,
                    "filename": "src\\features\\voting\\votingSection\\VotingSection.tsx"
                },
                {
                    "blank": 1,
                    "code": 12,
                    "comment": 0,
                    "filename": "src\\index.css"
                },
                {
                    "blank": 1,
                    "code": 7,
                    "comment": 0,
                    "filename": "src\\index.tsx"
                },
                {
                    "blank": 2,
                    "code": 5,
                    "comment": 0,
                    "filename": "src\\pages\\Homepage.tsx"
                },
                {
                    "blank": 0,
                    "code": 0,
                    "comment": 1,
                    "filename": "src\\react-app-env.d.ts"
                },
                {
                    "blank": 0,
                    "code": 1,
                    "comment": 4,
                    "filename": "src\\setupTests.ts"
                },
                {
                    "blank": 0,
                    "code": 5,
                    "comment": 0,
                    "filename": "src\\types\\CommentType.ts"
                },
                {
                    "blank": 2,
                    "code": 24,
                    "comment": 0,
                    "filename": "tsconfig.json"
                }
            ]
        }
    ]
}